localhttps/__init__.py
localhttps/app.py
localhttps/cert/__init__.py
localhttps/cert/ca.py
localhttps/cert/cert.py
localhttps/cli/__init__.py
localhttps/cli/commands/__init__.py
localhttps/cli/commands/init.py
localhttps/cli/commands/secure.py
localhttps/cli/commands/status.py
localhttps/cli/commands/unsecure.py
localhttps/cli/commands/use.py
localhttps/cli/context.py
localhttps/cmd.py
localhttps/keychain/__init__.py
localhttps/keychain/abc.py
localhttps/keychain/linux.py
localhttps/keychain/macos.py
localhttps/utils/cli.py
localhttps/utils/domain.py
localhttps-0.4.1.dist-info/entry_points.txt
localhttps-0.4.1.dist-info/LICENSE
localhttps-0.4.1.dist-info/WHEEL
localhttps-0.4.1.dist-info/METADATA
localhttps-0.4.1.dist-info/RECORD
