Metadata-Version: 2.1
Name: localhttps
Version: 0.4.1
Summary: HTTPS manager for local sites
License: MIT
Author: Tarik02
Author-email: Taras.Fomin@gmail.com
Requires-Python: >=3.10,<4.0
Classifier: License :: OSI Approved :: MIT License
Classifier: Programming Language :: Python :: 3
Classifier: Programming Language :: Python :: 3.10
Requires-Dist: aiofiles (>=0.8.0,<0.9.0)
Requires-Dist: aiopath (>=0.6.10,<0.7.0)
Requires-Dist: anyio (>=3.5.0,<4.0.0)
Requires-Dist: asyncclick (>=8.0.3,<9.0.0)
Requires-Dist: rich (>=11.2.0,<12.0.0)
